vibe_python/__init__.py
vibe_python/cli.py
vibe_python/config.py
vibe_python/core.py
vibe_python/vibe_python.py
vibepygo-0.1.0.dist-info/METADATA
vibepygo-0.1.0.dist-info/WHEEL
vibepygo-0.1.0.dist-info/entry_points.txt
vibepygo-0.1.0.dist-info/licenses/LICENSE
vibepygo-0.1.0.dist-info/RECORD
