Metadata-Version: 2.4
Name: vibepygo
Version: 0.1.0
Summary: LLM-interpreted Python
Author-email: qqqqqf <qingf622@outlook.com>
License: MIT License
License-File: LICENSE
Requires-Python: >=3.10
Requires-Dist: openai>=1.95.1
Requires-Dist: pydantic>=2.11.7
Requires-Dist: typing-extensions>=4.14.1
